cybersafe_iloveu/__init__.py
cybersafeiloveu-1.0.dist-info/METADATA
cybersafeiloveu-1.0.dist-info/WHEEL
cybersafeiloveu-1.0.dist-info/top_level.txt
cybersafeiloveu-1.0.dist-info/RECORD
