Metadata-Version: 2.1
Name: cybersafeiloveu
Version: 1.0
Summary: A Prank program for confessing love to your crush
Author: Min Sovan Sokheng(Cody) and CyberSafe Team
Author-email: hengmin1213@gmail.com
Keywords: python,Messagebox
Classifier: Development Status :: 1 - Planning
Classifier: Intended Audience :: Developers
Classifier: Programming Language :: Python :: 3
Classifier: Operating System :: Unix
Classifier: Operating System :: MacOS :: MacOS X
Classifier: Operating System :: Microsoft :: Windows
